mqsrv/__init__.py
mqsrv/base.py
mqsrv/client.py
mqsrv/config.py
mqsrv/contract.py
mqsrv/exc.py
mqsrv/rpc_utils.py
mqsrv/server.py
mqsrv/service.py
mqsrv-0.1.3.dist-info/LICENSE
mqsrv-0.1.3.dist-info/METADATA
mqsrv-0.1.3.dist-info/WHEEL
mqsrv-0.1.3.dist-info/top_level.txt
mqsrv-0.1.3.dist-info/RECORD
