Metadata-Version: 2.1
Name: mqsrv
Version: 0.1.3
Summary: A message queue-based RPC and event publish/subscribe system.
Home-page: https://github.com/tsinghtech/mqsrv
Author: daleydeng
Author-email: daleydeng@qingtong123.com
License: MIT
License-File: LICENSE
Requires-Dist: greenthread>=0.1.1
Requires-Dist: kombu>=5.1
Requires-Dist: tblib>=3.0
Requires-Dist: jsonpickle>=3.0
Requires-Dist: msgpack-python
Requires-Dist: msgpack-numpy
Requires-Dist: loguru>=0.5
Requires-Dist: gevent
